{
  "case_id": "chongqing-2025-female-low-index",
  "province": "chongqing",
  "city": "重庆",
  "gender": "女",
  "birth": "1975年11月",
  "work_start": "1995年10月",
  "retire_year": 2025,
  "retire_month": 11,
  "total_years": 30.17,
  "sight_years": 0,
  "pre_account_years": 0.25,
  "personal_account": 91263.47,
  "months": 195,
  "expected": {
    "basic_pension": 2117.64,
    "personal_pension": 468.02,
    "transitional_pension": null,
    "total": null
  },
  "notes": "重庆2025年11月退休女工（中人），1975-11生，1995-10参工。建账前0.25年(1995-10至1996-01)，缴费30年2月。低指数0.6702。使用2025年计发基数8240。独子待遇77.5元（表上未计入新办法）。渝人社发〔2013〕19号文。",
  "socialAvgBaseInput": 8240,
  "birth_year": 1975,
  "birth_month": 11,
  "work_year": 1995,
  "work_month": 10,
  "avg_index": 0.6702,
  "base_number": 8240,
  "base_prov": 8240
}