{
  "province": "henan",
  "name": "河南省",
  "account_start": {
    "year": 1996,
    "month": 1
  },
  "viewing_start": {
    "year": 1996,
    "month": 1
  },
  "base_rates": {
    "prov": {
      "2023": 6401,
      "2024": 6606,
      "2025": 6738,
      "2026": 6738
    },
    "zz": {
      "2023": 7800,
      "2024": 7800,
      "2025": 7800,
      "2026": 7800
    }
  },
  "avg_salary_history": {
    "1995": 362,
    "1996": 410.33,
    "1997": 435.42,
    "1998": 470.08,
    "1999": 511.33,
    "2000": 573.08,
    "2001": 655.67,
    "2002": 809.5,
    "2003": 886.57,
    "2004": 997.51,
    "2005": 1190.17,
    "2006": 1415.08,
    "2007": 1744.58,
    "2008": 2068,
    "2009": 2279.75,
    "2010": 2525.25,
    "2011": 2850.25,
    "2012": 3163.17,
    "2013": 3233.67,
    "2014": 3555.83,
    "2015": 3826.67,
    "2016": 4169,
    "2017": 4666.42,
    "2018": 5345.67,
    "2019": 5692.08,
    "2020": 5945.92,
    "2021": 6355.08,
    "2022": 6575.25,
    "2023": 7131.92,
    "2024": 7333.33,
    "_source": "河南省统计局：城镇非私营单位在岗职工平均工资（月均）",
    "_note": "缴费指数=个人缴费基数÷当年社平工资。1995-2004来自统计局公开数据，2005-2024来自用户直接提供的年值换算。"
  },
  "interest_rates": {
    "1995": 0.025,
    "1996": 0.025,
    "1997": 0.025,
    "1998": 0.025,
    "1999": 0.025,
    "2000": 0.025,
    "2001": 0.025,
    "2002": 0.025,
    "2003": 0.025,
    "2004": 0.025,
    "2005": 0.0226,
    "2006": 0.025,
    "2007": 0.025,
    "2008": 0.0393,
    "2009": 0.0225,
    "2010": 0.023,
    "2011": 0.025,
    "2012": 0.025,
    "2013": 0.0325,
    "2014": 0.025,
    "2015": 0.025
  },
  "monthly_payment_months": {
    "50.0": 195,
    "50.5": 192.5,
    "51.0": 190,
    "51.5": 187.5,
    "52.0": 185,
    "52.5": 182.5,
    "53.0": 180,
    "53.5": 177.5,
    "54.0": 175,
    "54.5": 172.5,
    "55.0": 170,
    "55.5": 167.5,
    "56.0": 164,
    "56.5": 161.5,
    "57.0": 158,
    "57.5": 155.5,
    "58.0": 152,
    "58.5": 149.5,
    "59.0": 145,
    "59.5": 142.5,
    "60.0": 139,
    "60.5": 136.1,
    "61.0": 132,
    "61.5": 128.6,
    "62.0": 125,
    "62.5": 121.4,
    "63.0": 117,
    "63.5": 113.4
  },
  "min_years": {
    "2025": 15,
    "2026": 15,
    "2027": 15,
    "2028": 15,
    "2029": 15,
    "2030": 15.5,
    "2031": 16,
    "2032": 16.5,
    "2033": 17,
    "2034": 17.5,
    "2035": 18,
    "2036": 18.5,
    "2037": 19,
    "2038": 19.5,
    "2039": 20,
    "2040": 20,
    "2041": 20,
    "2042": 20,
    "2043": 20,
    "2044": 20,
    "2045": 20
  },
  "delay_retirement": {
    "effective_date": "2026-01-01",
    "male": {
      "base_year": 1965,
      "step": 4,
      "cap_months": 36
    },
    "fc": {
      "base_year": 1970,
      "step": 4,
      "cap_months": 36
    },
    "fw55": {
      "base_year": 1975,
      "step": 2,
      "cap_months": 60
    }
  },
  "modules": {
    "basic_pension": {
      "enabled": true,
      "rate_per_year": 0.01,
      "formula": "(退休地计发基数 + 退休地计发基数 × 指数) / 2 × 累计缴费年限 × 1%",
      "formula_type": "henan"
    },
    "extra_pension": {
      "enabled": false,
      "formula": "暂不启用（需确认河南是否有增发养老金）"
    },
    "personal_account": {
      "enabled": true,
      "formula": "个人账户累计储存额 / 计发月数"
    },
    "transitional_pension": {
      "enabled": true,
      "coefficient": 0.013,
      "formula": "退休地计发基数 × 过渡性指数 × 视同缴费年限 × 1.3%",
      "formula_type": "henan"
    },
    "special_addition": {
      "enabled": true,
      "type": "zhengzhou_subsidy",
      "subsidy_param": 8.85,
      "formula": "[(实际缴费年限 × 8.85) / (全部年限 × 1%)] × (郑州计发基数/7933)，郑州市政府令第161号（2026年参数）"
    }
  },
  "cities": [
    {
      "code": "prov",
      "name": "全省默认"
    },
    {
      "code": "zz",
      "name": "郑州市"
    }
  ],
  "notes": {
    "policy": "河南省：基础养老金和过渡性养老金均用全省计发基数×指数计算指数化工资（formula_type:henan）。过渡系数1.3%。无增发养老金。郑州有独立基数且有'过渡性补贴'（已实现，市政府令161号）。",
    "data_source": "豫人社官方文件+3份核定表验证通过",
    "verified_count": 7,
    "base_2023": "全省6401/郑州7800（核定表确认）",
    "zhengzhou_subsidy_param": "过渡性补贴参数8.85（2026年核定表确认，参数随年度递增）",
    "base_2024": "全省6606（官方文件确认）",
    "base_2025": "全省6738（核定表确认）",
    "avg_salary_source": "1995-2024完整：城镇非私营单位在岗职工平均工资（河南统计局，用户提供）",
    "todo": [
      "实现郑州'过渡性补贴'（case3=419.9元/月）"
    ]
  }
}