{
  "province": "gansu",
  "name": "甘肃省",
  "account_start": {
    "year": 1996,
    "month": 1
  },
  "viewing_start": {
    "year": 1996,
    "month": 1
  },
  "base_rates": {
    "prov": {
      "1995": 301.92,
      "1996": 348.54,
      "1997": 374.46,
      "1998": 382.32,
      "1999": 419.82,
      "2000": 478.56,
      "2001": 540.0,
      "2002": 611.94,
      "2003": 683.28,
      "2004": 785.82,
      "2005": 931.8,
      "2006": 1153.68,
      "2007": 1370.64,
      "2008": 1584.24,
      "2009": 1781.28,
      "2010": 2023.74,
      "2011": 2279.52,
      "2012": 2554.5,
      "2013": 2859.12,
      "2014": 3147.6,
      "2015": 3491.82,
      "2016": 3813.72,
      "2017": 4158.3,
      "2018": 3922.98,
      "2019": 4148.16,
      "2020": 4494.36,
      "2021": 4775.82,
      "2022": 5089.86,
      "2023": 5089.86,
      "2024": 5089.86,
      "2025": 5220.0,
      "2026": 5364.0
    }
  },
  "interest_rates": {
    "1995": 0.025,
    "1996": 0.025,
    "1997": 0.025,
    "1998": 0.025,
    "1999": 0.025,
    "2000": 0.025,
    "2001": 0.025,
    "2002": 0.025,
    "2003": 0.025,
    "2004": 0.025,
    "2005": 0.0226,
    "2006": 0.025,
    "2007": 0.025,
    "2008": 0.0393,
    "2009": 0.0225,
    "2010": 0.023,
    "2011": 0.025,
    "2012": 0.025,
    "2013": 0.0325,
    "2014": 0.025,
    "2015": 0.025,
    "2016": 0.0831,
    "2017": 0.0712,
    "2018": 0.0829,
    "2019": 0.0761,
    "2020": 0.0604,
    "2021": 0.0669,
    "2022": 0.0397,
    "2023": 0.0397,
    "2024": 0.0262,
    "2025": 0.015
  },
  "monthly_payment_months": {
    "50.0": 195.0,
    "50.5": 192.5,
    "51.0": 190.0,
    "51.5": 187.5,
    "52.0": 185.0,
    "52.5": 182.5,
    "53.0": 180.0,
    "53.5": 177.5,
    "54.0": 175.0,
    "54.5": 172.5,
    "55.0": 170.0,
    "55.5": 167.5,
    "56.0": 164.0,
    "56.5": 161.5,
    "57.0": 158.0,
    "57.5": 155.5,
    "58.0": 152.0,
    "58.5": 149.5,
    "59.0": 145.0,
    "59.5": 142.5,
    "60.0": 139.0,
    "60.5": 136.1,
    "61.0": 132.0,
    "61.5": 128.6,
    "62.0": 125.0,
    "62.5": 121.4,
    "63.0": 117.0,
    "63.5": 113.4
  },
  "min_years": {
    "2025": 15,
    "2026": 15,
    "2027": 15,
    "2028": 15,
    "2029": 15,
    "2030": 15.5,
    "2031": 16,
    "2032": 16.5,
    "2033": 17,
    "2034": 17.5,
    "2035": 18,
    "2036": 18.5,
    "2037": 19,
    "2038": 19.5,
    "2039": 20,
    "2040": 20,
    "2041": 20,
    "2042": 20,
    "2043": 20,
    "2044": 20,
    "2045": 20
  },
  "delay_retirement": {
    "effective_date": "2026-01-01",
    "male": {
      "base_year": 1965,
      "step": 4,
      "cap_months": 36
    },
    "fc": {
      "base_year": 1970,
      "step": 4,
      "cap_months": 36
    },
    "fw55": {
      "base_year": 1975,
      "step": 2,
      "cap_months": 60
    }
  },
  "modules": {
    "basic_pension": {
      "enabled": true,
      "rate_per_year": 0.01,
      "formula": "(退休地计发基数 + 全省计发基数 × 指数) / 2 × 累计缴费年限 × 1%"
    },
    "extra_pension": {
      "enabled": true,
      "trigger": {
        "type": "total_years",
        "threshold": 20
      },
      "brackets": [
        {
          "from": 21,
          "to": 25,
          "years": 5,
          "rate": 0.0015
        },
        {
          "from": 26,
          "to": 30,
          "years": 5,
          "rate": 0.002
        },
        {
          "from": 31,
          "to": null,
          "years": null,
          "rate": 0.0025
        }
      ],
      "formula": "累计缴费年限超20年部分分段累加计算"
    },
    "personal_account": {
      "enabled": true,
      "formula": "个人账户累计储存额 / 计发月数"
    },
    "transitional_pension": {
      "enabled": true,
      "coefficient_over_20": 0.014,
      "coefficient_under_20": 0.012,
      "formula": "全省计发基数 × 视同缴费年限 × 指数 × 系数(>20年:1.4%,≤20年:1.2%)"
    },
    "special_addition": {
      "enabled": false
    }
  },
  "cities": [
    {
      "code": "prov",
      "name": "全省（默认）"
    }
  ],
  "notes": {
    "policy": "甘肃省养老金计发基数基于估算数据（参考山东省社平工资×0.72系数），实际数据请向当地社保部门核实。",
    "data_source": "估算数据，仅供参考",
    "special_notes": "此配置文件为估算数据，正式使用前请核实当地真实计发基数。"
  }
}